     0x0: [ 0x10] BIPUSH 0x0
     0x2: [ 0x59] DUP
     0x3: [ 0x36] ISTORE 0
     0x5: [ 0x36] ISTORE 1
     0x7: [ 0x10] BIPUSH 0x20
     0x9: [ 0xFD] OUT
     0xA: [ 0x13] LDC_W 0[=0x40]
     0xD: [ 0xB6] INVOKEVIRTUAL 1[=0x43]
    0x10: [ 0x36] ISTORE 0
    0x12: [ 0x10] BIPUSH 0x2B
    0x14: [ 0xFD] OUT
    0x15: [ 0x13] LDC_W 0[=0x40]
    0x18: [ 0xB6] INVOKEVIRTUAL 1[=0x43]
    0x1B: [ 0x36] ISTORE 1
    0x1D: [ 0x10] BIPUSH 0x3D
    0x1F: [ 0x59] DUP
    0x20: [ 0x59] DUP
    0x21: [ 0x59] DUP
    0x22: [ 0x59] DUP
    0x23: [ 0x59] DUP
    0x24: [ 0x59] DUP
    0x25: [ 0x59] DUP
    0x26: [ 0xFD] OUT
    0x27: [ 0xFD] OUT
    0x28: [ 0xFD] OUT
    0x29: [ 0xFD] OUT
    0x2A: [ 0xFD] OUT
    0x2B: [ 0xFD] OUT
    0x2C: [ 0xFD] OUT
    0x2D: [ 0xFD] OUT
    0x2E: [ 0x10] BIPUSH 0xA
    0x30: [ 0xFD] OUT
    0x31: [ 0x15] ILOAD 0
    0x33: [ 0x15] ILOAD 1
    0x35: [ 0x60] IADD
    0x36: [ 0x36] ISTORE 2
    0x38: [ 0x13] LDC_W 0[=0x40]
    0x3B: [ 0x15] ILOAD 2
    0x3D: [ 0xB6] INVOKEVIRTUAL 2[=0x94]
    0x40: [ 0xFF] HALT
    0x41: [  0x0] NOP
    0x42: [  0x0] NOP
    0x43: [  0x0] NOP
    0x44: [  0x1] -
    0x45: [  0x0] NOP
    0x46: [  0x1] -
    0x47: [ 0x10] BIPUSH 0x0
    0x49: [ 0x36] ISTORE 1
    0x4B: [ 0xFC] IN
    0x4C: [ 0x59] DUP
    0x4D: [ 0x10] BIPUSH 0xA
    0x4F: [ 0x9F] IF_ICMPEQ 65
    0x52: [ 0x59] DUP
    0x53: [ 0x10] BIPUSH 0x30
    0x55: [ 0x64] ISUB
    0x56: [ 0x9B] IFLT 54
    0x59: [ 0x59] DUP
    0x5A: [ 0x10] BIPUSH 0x3A
    0x5C: [ 0x64] ISUB
    0x5D: [ 0x9B] IFLT 26
    0x60: [ 0x59] DUP
    0x61: [ 0x10] BIPUSH 0x41
    0x63: [ 0x64] ISUB
    0x64: [ 0x9B] IFLT 40
    0x67: [ 0x59] DUP
    0x68: [ 0x10] BIPUSH 0x46
    0x6A: [ 0x5F] SWAP
    0x6B: [ 0x64] ISUB
    0x6C: [ 0x9B] IFLT 32
    0x6F: [ 0x59] DUP
    0x70: [ 0xFD] OUT
    0x71: [ 0x10] BIPUSH 0x37
    0x73: [ 0x64] ISUB
    0x74: [ 0xA7] GOTO 8
    0x77: [ 0x59] DUP
    0x78: [ 0xFD] OUT
    0x79: [ 0x10] BIPUSH 0x30
    0x7B: [ 0x64] ISUB
    0x7C: [ 0x15] ILOAD 1
    0x7E: [ 0x59] DUP
    0x7F: [ 0x60] IADD
    0x80: [ 0x59] DUP
    0x81: [ 0x60] IADD
    0x82: [ 0x59] DUP
    0x83: [ 0x60] IADD
    0x84: [ 0x59] DUP
    0x85: [ 0x60] IADD
    0x86: [ 0x60] IADD
    0x87: [ 0x36] ISTORE 1
    0x89: [ 0xA7] GOTO -62
    0x8C: [ 0x57] POP
    0x8D: [ 0xA7] GOTO -66
    0x90: [ 0xFD] OUT
    0x91: [ 0x15] ILOAD 1
    0x93: [ 0xAC] IRETURN
    0x94: [  0x0] NOP
    0x95: [  0x2] -
    0x96: [  0x0] NOP
    0x97: [  0x2] -
    0x98: [ 0x10] BIPUSH 0x9
    0x9A: [ 0x36] ISTORE 3
    0x9C: [ 0x10] BIPUSH 0x1
    0x9E: [ 0x36] ISTORE 2
    0xA0: [ 0x10] BIPUSH 0x0
    0xA2: [ 0x15] ILOAD 3
    0xA4: [ 0x10] BIPUSH 0x1
    0xA6: [ 0x64] ISUB
    0xA7: [ 0x59] DUP
    0xA8: [ 0x99] IFEQ 76
    0xAB: [ 0x36] ISTORE 3
    0xAD: [ 0x15] ILOAD 1
    0xAF: [ 0x15] ILOAD 2
    0xB1: [ 0x7E] IAND
    0xB2: [ 0x99] IFEQ 6
    0xB5: [ 0x10] BIPUSH 0x1
    0xB7: [ 0x60] IADD
    0xB8: [ 0x15] ILOAD 2
    0xBA: [ 0x59] DUP
    0xBB: [ 0x60] IADD
    0xBC: [ 0x36] ISTORE 2
    0xBE: [ 0x15] ILOAD 1
    0xC0: [ 0x15] ILOAD 2
    0xC2: [ 0x7E] IAND
    0xC3: [ 0x99] IFEQ 6
    0xC6: [ 0x10] BIPUSH 0x2
    0xC8: [ 0x60] IADD
    0xC9: [ 0x15] ILOAD 2
    0xCB: [ 0x59] DUP
    0xCC: [ 0x60] IADD
    0xCD: [ 0x36] ISTORE 2
    0xCF: [ 0x15] ILOAD 1
    0xD1: [ 0x15] ILOAD 2
    0xD3: [ 0x7E] IAND
    0xD4: [ 0x99] IFEQ 6
    0xD7: [ 0x10] BIPUSH 0x4
    0xD9: [ 0x60] IADD
    0xDA: [ 0x15] ILOAD 2
    0xDC: [ 0x59] DUP
    0xDD: [ 0x60] IADD
    0xDE: [ 0x36] ISTORE 2
    0xE0: [ 0x15] ILOAD 1
    0xE2: [ 0x15] ILOAD 2
    0xE4: [ 0x7E] IAND
    0xE5: [ 0x99] IFEQ 6
    0xE8: [ 0x10] BIPUSH 0x8
    0xEA: [ 0x60] IADD
    0xEB: [ 0x15] ILOAD 2
    0xED: [ 0x59] DUP
    0xEE: [ 0x60] IADD
    0xEF: [ 0x36] ISTORE 2
    0xF1: [ 0xA7] GOTO -81
    0xF4: [ 0x57] POP
    0xF5: [ 0x57] POP
    0xF6: [ 0x10] BIPUSH 0x9
    0xF8: [ 0x36] ISTORE 3
    0xFA: [ 0x15] ILOAD 3
    0xFC: [ 0x10] BIPUSH 0x1
    0xFE: [ 0x64] ISUB
    0xFF: [ 0x59] DUP
   0x100: [ 0x99] IFEQ 26
   0x103: [ 0x36] ISTORE 3
   0x105: [ 0x59] DUP
   0x106: [ 0x10] BIPUSH 0xA
   0x108: [ 0x64] ISUB
   0x109: [ 0x9B] IFLT 10
   0x10C: [ 0x10] BIPUSH 0x37
   0x10E: [ 0x60] IADD
   0x10F: [ 0xFD] OUT
   0x110: [ 0xA7] GOTO -22
   0x113: [ 0x10] BIPUSH 0x30
   0x115: [ 0x60] IADD
   0x116: [ 0xFD] OUT
   0x117: [ 0xA7] GOTO -29
   0x11A: [ 0x10] BIPUSH 0xA
   0x11C: [ 0xFD] OUT
   0x11D: [ 0xAC] IRETURN
